django_simple_buefy/__init__.py
django_simple_buefy/apps.py
django_simple_buefy/constants.py
django_simple_buefy/finders.py
django_simple_buefy/settings.py
django_simple_buefy/css/buefy.css
django_simple_buefy/css/buefy.min.css
django_simple_buefy/js/buefy.esm.js
django_simple_buefy/js/buefy.esm.min.js
django_simple_buefy/js/buefy.js
django_simple_buefy/js/buefy.min.js
django_simple_buefy/js/vue.esm.js
django_simple_buefy/js/vue.esm.min.js
django_simple_buefy/js/vue.js
django_simple_buefy/js/vue.min.js
django_simple_buefy/js/components/autocomplete/index.js
django_simple_buefy/js/components/autocomplete/index.min.js
django_simple_buefy/js/components/button/index.js
django_simple_buefy/js/components/button/index.min.js
django_simple_buefy/js/components/carousel/index.js
django_simple_buefy/js/components/carousel/index.min.js
django_simple_buefy/js/components/checkbox/index.js
django_simple_buefy/js/components/checkbox/index.min.js
django_simple_buefy/js/components/clockpicker/index.js
django_simple_buefy/js/components/clockpicker/index.min.js
django_simple_buefy/js/components/collapse/index.js
django_simple_buefy/js/components/collapse/index.min.js
django_simple_buefy/js/components/datepicker/index.js
django_simple_buefy/js/components/datepicker/index.min.js
django_simple_buefy/js/components/datetimepicker/index.js
django_simple_buefy/js/components/datetimepicker/index.min.js
django_simple_buefy/js/components/dialog/index.js
django_simple_buefy/js/components/dialog/index.min.js
django_simple_buefy/js/components/dropdown/index.js
django_simple_buefy/js/components/dropdown/index.min.js
django_simple_buefy/js/components/field/index.js
django_simple_buefy/js/components/field/index.min.js
django_simple_buefy/js/components/icon/index.js
django_simple_buefy/js/components/icon/index.min.js
django_simple_buefy/js/components/input/index.js
django_simple_buefy/js/components/input/index.min.js
django_simple_buefy/js/components/loading/index.js
django_simple_buefy-1.0.4.dist-info/LICENSE
django_simple_buefy-1.0.4.dist-info/METADATA
django_simple_buefy-1.0.4.dist-info/WHEEL
django_simple_buefy-1.0.4.dist-info/top_level.txt
django_simple_buefy-1.0.4.dist-info/RECORD
