Metadata-Version: 2.1
Name: django-simple-buefy
Version: 1.0.4
Summary: Django application to add Buefy, Bulma and Vue to your project
Home-page: https://github.com/comect/django-simple-buefy
Author: Comect
Author-email: gdude2002@gmail.com
License: MIT
Platform: UNKNOWN
Classifier: Environment :: Web Environment
Classifier: Framework :: Django
Classifier: Framework :: Django :: 2.0
Classifier: Framework :: Django :: 2.1
Classifier: License :: OSI Approved :: MIT License
Classifier: Operating System :: OS Independent
Classifier: Programming Language :: Python
Classifier: Programming Language :: Python :: 3.6
Classifier: Programming Language :: Python :: 3.7
Classifier: Topic :: Internet :: WWW/HTTP
Classifier: Topic :: Internet :: WWW/HTTP :: Dynamic Content
Classifier: Topic :: Software Development :: Libraries :: Python Modules
Requires-Dist: Django (>=2.0)
Requires-Dist: libsass (~=0.19)
Provides-Extra: dev
Requires-Dist: black ; extra == 'dev'
Requires-Dist: flake8 (~=3.7) ; extra == 'dev'
Requires-Dist: flake8-bugbear (~=19.8) ; extra == 'dev'
Requires-Dist: flake8-import-order (~=0.18) ; extra == 'dev'
Requires-Dist: flake8-tidy-imports (~=2.0) ; extra == 'dev'
Requires-Dist: flake8-todo (~=0.7) ; extra == 'dev'
Requires-Dist: flake8-string-format (~=0.2) ; extra == 'dev'
Requires-Dist: pdoc (~=0.3) ; extra == 'dev'
Requires-Dist: pre-commit (~=1.18) ; extra == 'dev'
Requires-Dist: PyGithub (~=1.43) ; extra == 'dev'
Requires-Dist: wheel (~=0.33) ; extra == 'dev'
